sphinx_social_cards/__init__.py
sphinx_social_cards/colors.py
sphinx_social_cards/fonts.py
sphinx_social_cards/generator.py
sphinx_social_cards/images.py
sphinx_social_cards/metadata.py
sphinx_social_cards/.fonts/Roboto Condensed italic (latin 100).ttf
sphinx_social_cards/.fonts/Roboto Condensed italic (latin 200).ttf
sphinx_social_cards/.fonts/Roboto Condensed italic (latin 300).ttf
sphinx_social_cards/.fonts/Roboto Condensed italic (latin 400).ttf
sphinx_social_cards/.fonts/Roboto Condensed italic (latin 500).ttf
sphinx_social_cards/.fonts/Roboto Condensed italic (latin 600).ttf
sphinx_social_cards/.fonts/Roboto Condensed italic (latin 700).ttf
sphinx_social_cards/.fonts/Roboto Condensed italic (latin 800).ttf
sphinx_social_cards/.fonts/Roboto Condensed italic (latin 900).ttf
sphinx_social_cards/.fonts/Roboto Condensed normal (latin 100).ttf
sphinx_social_cards/.fonts/Roboto Condensed normal (latin 200).ttf
sphinx_social_cards/.fonts/Roboto Condensed normal (latin 300).ttf
sphinx_social_cards/.fonts/Roboto Condensed normal (latin 400).ttf
sphinx_social_cards/.fonts/Roboto Condensed normal (latin 500).ttf
sphinx_social_cards/.fonts/Roboto Condensed normal (latin 600).ttf
sphinx_social_cards/.fonts/Roboto Condensed normal (latin 700).ttf
sphinx_social_cards/.fonts/Roboto Condensed normal (latin 800).ttf
sphinx_social_cards/.fonts/Roboto Condensed normal (latin 900).ttf
sphinx_social_cards/.fonts/Roboto Condensed.json
sphinx_social_cards/.fonts/Roboto Flex normal (latin 400).ttf
sphinx_social_cards/.fonts/Roboto Flex.json
sphinx_social_cards/.fonts/Roboto Mono italic (latin 100).ttf
sphinx_social_cards/.fonts/Roboto Mono italic (latin 200).ttf
sphinx_social_cards/.fonts/Roboto Mono italic (latin 300).ttf
sphinx_social_cards/.fonts/Roboto Mono italic (latin 400).ttf
sphinx_social_cards/.fonts/Roboto Mono italic (latin 500).ttf
sphinx_social_cards/.fonts/Roboto Mono italic (latin 600).ttf
sphinx_social_cards/.fonts/Roboto Mono italic (latin 700).ttf
sphinx_social_cards-0.5.0.dist-info/licenses/LICENSE.md
sphinx_social_cards-0.5.0.dist-info/METADATA
sphinx_social_cards-0.5.0.dist-info/WHEEL
sphinx_social_cards-0.5.0.dist-info/top_level.txt
sphinx_social_cards-0.5.0.dist-info/RECORD
