Metadata-Version: 2.4
Name: sphinx-social-cards
Version: 0.5.0
Summary: Generate social media cards for documentation pages with Sphinx
Author-email: Brendan Doherty <2bndy5@gmail.com>
License-Expression: MIT
Project-URL: Documentation, https://2bndy5.github.io/sphinx-social-cards
Project-URL: Source, http://github.com/2bndy5/sphinx-social-cards
Keywords: sphinx,social,cards,previews
Classifier: Development Status :: 4 - Beta
Classifier: Environment :: Console
Classifier: Environment :: Web Environment
Classifier: Framework :: Sphinx :: Extension
Classifier: Intended Audience :: Developers
Classifier: Operating System :: OS Independent
Classifier: Programming Language :: Python
Classifier: Programming Language :: Python :: 3
Classifier: Topic :: Documentation
Classifier: Topic :: Documentation :: Sphinx
Classifier: Topic :: Utilities
Requires-Python: >=3.9
License-File: LICENSE.md
Requires-Dist: fontawesome-free-pack>=7.0.1
Requires-Dist: material-design-icons-pack>=7.4.47
Requires-Dist: octicons-pack>=19.18.0
Requires-Dist: pydantic>=2.4
Requires-Dist: pydantic-extra-types>=2.10.5
Requires-Dist: pyside6>=6.9.2
Requires-Dist: pyyaml>=6.0.2
Requires-Dist: requests>=2.32.5
Requires-Dist: simple-icons-pack>=15.15.0
Requires-Dist: sphinx>=4.5
Provides-Extra: github
Requires-Dist: appdirs>=1.4.4; extra == "github"
Dynamic: license-file
